<usereventscript scriptid="customscript_rsc_finan_convertpropcontr">
  <description></description>
  <isinactive>F</isinactive>
  <name>RSC - JUnix - Convert Lead To Contract</name>
  <notifyadmins>F</notifyadmins>
  <notifyemails></notifyemails>
  <notifyowner>T</notifyowner>
  <notifyuser>F</notifyuser>
  <scriptfile>[/SuiteScripts/JunixCadastro/rsc_finan_convertpropcontr.js]</scriptfile>
  <scriptdeployments>
    <scriptdeployment scriptid="customdeploy_rsc_finan_convertpropcontr">
      <allemployees>F</allemployees>
      <alllocalizationcontexts>T</alllocalizationcontexts>
      <allpartners>F</allpartners>
      <allroles>F</allroles>
      <audslctrole>ADMINISTRATOR</audslctrole>
      <eventtype></eventtype>
      <executioncontext>ACTION|ADVANCEDREVREC|BANKCONNECTIVITY|BANKSTATEMENTPARSER|BUNDLEINSTALLATION|CLIENT|CONSOLRATEADJUSTOR|CSVIMPORT|CUSTOMGLLINES|CUSTOMMASSUPDATE|DATASETBUILDER|DEBUGGER|EMAILCAPTURE|FICONNECTIVITY|FIPARSER|MAPREDUCE|OTHER|PAYMENTGATEWAY|PAYMENTPOSTBACK|PLATFORMEXTENSION|PORTLET|PROMOTIONS|RECORDACTION|RESTLET|RESTWEBSERVICES|SCHEDULED|SDFINSTALLATION|SHIPPINGPARTNERS|SUITELET|TAXCALCULATION|USEREVENT|USERINTERFACE|WEBSERVICES|WORKBOOKBUILDER|WORKFLOW</executioncontext>
      <isdeployed>T</isdeployed>
      <loglevel>DEBUG</loglevel>
      <recordtype>INVOICE</recordtype>
      <runasrole></runasrole>
      <status>RELEASED</status>
    </scriptdeployment>
  </scriptdeployments>
</usereventscript>